WorthData.py
WorthData-1.1.1.dist-info/METADATA
WorthData-1.1.1.dist-info/WHEEL
WorthData-1.1.1.dist-info/top_level.txt
WorthData-1.1.1.dist-info/RECORD
