Metadata-Version: 2.1
Name: WorthData
Version: 1.1.1
Summary: WorthData is a simple database that can handle big amount of data
Home-page: https://github.com/IM-code111/jsonbase-1.0.0
Author: WinXpDev
Author-email: muhammad184276@gmail.com
License: UNKNOWN
Platform: UNKNOWN
Classifier: Programming Language :: Python :: 3
Classifier: License :: OSI Approved :: MIT License
Classifier: Operating System :: OS Independent
Requires-Python: >=3.6
